{
  "1969": [
    "moon-landing"
  ],
  "1989": [
    "fall-of-berlin-wall-1989",
    "tiananmen-square-protests-1989"
  ],
  "1990": [
    "nelson-mandela-release-1990"
  ],
  "1991": [
    "fall-of-the-soviet-union-1991"
  ],
  "1998": [
    "good-friday-agreement-1998"
  ],
  "2001": [
    "september-11-attacks-2001"
  ],
  "2004": [
    "european-union-expansion-2004",
    "indian-ocean-tsunami-2004"
  ],
  "2005": [
    "hurricane-katrina-2005"
  ],
  "2008": [
    "beijing-olympics-2008"
  ],
  "2011": [
    "fukushima-disaster-2011"
  ],
  "2014": [
    "russian-annexation-of-crimea-2014"
  ],
  "2015": [
    "paris-climate-agreement-2015"
  ],
  "2021": [
    "us-capitol-attack-2021"
  ],
  "2001-2021": [
    "afghanistan-war"
  ],
  "3100 BC - 30 BC": [
    "ancient-egypt"
  ],
  "2010-2012": [
    "arab-spring"
  ],
  "2013-Present": [
    "black-lives-matter-movement"
  ],
  "1966-1982": [
    "black-panther-party"
  ],
  "1992-1995": [
    "bosnian-war-1992-1995"
  ],
  "2016-2020": [
    "brexit-2016-2020"
  ],
  "1954-1968": [
    "civil-rights-movement"
  ],
  "2018-Present": [
    "climate-strike-movement"
  ],
  "1947-1991": [
    "cold-war"
  ],
  "2019-2023": [
    "covid-19-pandemic"
  ],
  "1970s": [
    "disco-era"
  ],
  "2000-2002": [
    "dot-com-bubble-burst-2000"
  ],
  "1999-2002": [
    "euro-currency-launch-1999-2002"
  ],
  "2015-2016": [
    "european-migrant-crisis-2015"
  ],
  "476 AD": [
    "fall-of-rome"
  ],
  "1789-1799": [
    "french-revolution"
  ],
  "2007-2009": [
    "global-financial-crisis-2008"
  ],
  "2001-Present": [
    "global-war-on-terror"
  ],
  "1920s-1930s": [
    "harlem-renaissance"
  ],
  "2019-2020": [
    "hong-kong-protests-2019"
  ],
  "1760-1840": [
    "industrial-revolution"
  ],
  "2003-2011": [
    "iraq-war"
  ],
  "1998-1999": [
    "kosovo-war-1998-1999"
  ],
  "2017-Present": [
    "me-too-movement"
  ],
  "2004-2015": [
    "rise-of-social-media-2004-2015"
  ],
  "1920s": [
    "roaring-twenties"
  ],
  "2022-Present": [
    "russian-invasion-of-ukraine-2022"
  ],
  "2007-Present": [
    "smartphone-revolution-2007"
  ],
  "2011-Present": [
    "syrian-civil-war"
  ],
  "1939-1945": [
    "world-war-ii"
  ],
  "1999-2000": [
    "y2k-bug-2000"
  ]
}