{
  "id": "gas",
  "type": "lingo",
  "name": "Gas",
  "aliases": ["Loud", "Zaza"],
  "era": "2010s-Present",
  "tags": ["marijuana", "quality", "energy"],
  "one_liner": "High-quality marijuana or something that is exceptionally good/energetic.",
  "angles": ["the fuel of the studio", "top-shelf quality", "pumping the gas"],
  "bar_seeds": ["smoking gas", "that song is gas", "don't gas him up"],
  "meaning": "1. High grade cannabis. 2. Something impressive or 'fire'.",
  "usage": "Lyrics often play on the dual meaning of fuel/energy and drugs.",
  "origin": "Various",
  "region": "Global",
  "example_lines": ["This beat is pure gas", "Smelling like gas"],
  "related_ids": [],
  "created_at": "2023-10-27T10:00:00Z",
  "updated_at": "2023-10-27T10:00:00Z",
  "sources": []
}
